get_assemblies/__init__.py
get_assemblies/__main__.py
get_assemblies/__version__.py
get_assemblies/biosample.py
get_assemblies/pbar.py
get_assemblies-0.11.3.dist-info/LICENSE
get_assemblies-0.11.3.dist-info/METADATA
get_assemblies-0.11.3.dist-info/WHEEL
get_assemblies-0.11.3.dist-info/entry_points.txt
get_assemblies-0.11.3.dist-info/top_level.txt
get_assemblies-0.11.3.dist-info/RECORD
