Metadata-Version: 2.1
Name: get-assemblies
Version: 0.11.3
Summary: NCBI E-utilities wrapper for assembly downloads
Home-page: https://github.com/davised/get_assemblies
Author: Edward Davis
Author-email: ed@cgrb.oregonstate.edu
Maintainer: Edward Davis
Maintainer-email: ed@cgrb.oregonstate.edu
License: Custom
Classifier: Development Status :: 4 - Beta
Classifier: Intended Audience :: Science/Research
Classifier: Natural Language :: English
Classifier: License :: Free for non-commercial use
Classifier: Operating System :: OS Independent
Classifier: Programming Language :: Python :: 3.7
Classifier: Programming Language :: Python :: 3.8
Classifier: Programming Language :: Python :: 3.9
Classifier: Programming Language :: Python :: Implementation :: PyPy
Classifier: Topic :: Scientific/Engineering :: Bio-Informatics
License-File: LICENSE
Requires-Dist: rich (>=10.0.0)
